langchain_compensation/__init__.py
langchain_compensation/agents.py
langchain_compensation/batch.py
langchain_compensation/checkpoint.py
langchain_compensation/errors.py
langchain_compensation/extraction.py
langchain_compensation/middleware.py
langchain_compensation/retry.py
langchain_compensation-0.5.8.dist-info/METADATA
langchain_compensation-0.5.8.dist-info/WHEEL
langchain_compensation-0.5.8.dist-info/licenses/LICENSE
langchain_compensation-0.5.8.dist-info/RECORD
