Metadata-Version: 2.4
Name: langchain-compensation
Version: 0.5.8
Summary: Composable compensation middleware for LangChain agents with automatic rollback, pluggable strategies, multi-agent support, and LLM-driven parameter extraction
Project-URL: Homepage, https://github.com/Kavirubc/langchain-compensation
Project-URL: Repository, https://github.com/Kavirubc/langchain-compensation
Project-URL: Documentation, https://github.com/Kavirubc/langchain-compensation#readme
Project-URL: Issues, https://github.com/Kavirubc/langchain-compensation/issues
Author-email: Kaviru <hapuarachchikaviru@gmail.com>
License: MIT
License-File: LICENSE
Keywords: agents,compensation,fault-tolerance,langchain,middleware,multi-agent,rollback,saga
Classifier: Development Status :: 4 - Beta
Classifier: Intended Audience :: Developers
Classifier: License :: OSI Approved :: MIT License
Classifier: Programming Language :: Python :: 3
Classifier: Programming Language :: Python :: 3.9
Classifier: Programming Language :: Python :: 3.10
Classifier: Programming Language :: Python :: 3.11
Classifier: Programming Language :: Python :: 3.12
Classifier: Programming Language :: Python :: 3.13
Classifier: Topic :: Scientific/Engineering :: Artificial Intelligence
Classifier: Topic :: Software Development :: Libraries :: Python Modules
Requires-Python: >=3.9
Requires-Dist: langchain-core>=0.3.0
Requires-Dist: langchain>=0.3.0
Requires-Dist: langgraph>=0.2.0
Provides-Extra: anthropic
Requires-Dist: langchain-anthropic>=0.1.0; extra == 'anthropic'
Provides-Extra: dev
Requires-Dist: black>=23.0.0; extra == 'dev'
Requires-Dist: mypy>=1.0.0; extra == 'dev'
Requires-Dist: pytest-asyncio>=0.21.0; extra == 'dev'
Requires-Dist: pytest>=7.0.0; extra == 'dev'
Requires-Dist: ruff>=0.1.0; extra == 'dev'
Provides-Extra: llm
Requires-Dist: langchain-anthropic>=0.1.0; extra == 'llm'
Requires-Dist: langchain-openai>=0.1.0; extra == 'llm'
Provides-Extra: openai
Requires-Dist: langchain-openai>=0.1.0; extra == 'openai'
